flanaapis/__init__.py
flanaapis/exceptions.py
flanaapis/main.py
flanaapis/geolocation/__init__.py
flanaapis/geolocation/functions.py
flanaapis/geolocation/google_maps.py
flanaapis/geolocation/models.py
flanaapis/geolocation/open_street_map.py
flanaapis/geolocation/routes.py
flanaapis/scraping/__init__.py
flanaapis/scraping/constants.py
flanaapis/scraping/functions.py
flanaapis/scraping/google_weather_scraper.py
flanaapis/scraping/instagram.py
flanaapis/scraping/reddit.py
flanaapis/scraping/routes.py
flanaapis/scraping/tiktok.py
flanaapis/scraping/twitter.py
flanaapis/scraping/yt_dlp_wrapper.py
flanaapis/weather/__init__.py
flanaapis/weather/constants.py
flanaapis/weather/functions.py
flanaapis/weather/google.py
flanaapis/weather/models.py
flanaapis/weather/open_weather_map.py
flanaapis/weather/routes.py
flanaapis/weather/visual_crossing.py
flanaapis-1.6.2.dist-info/LICENSE
flanaapis-1.6.2.dist-info/METADATA
flanaapis-1.6.2.dist-info/WHEEL
flanaapis-1.6.2.dist-info/top_level.txt
flanaapis-1.6.2.dist-info/RECORD
