Metadata-Version: 2.1
Name: flanaapis
Version: 1.6.2
Summary: Set of functions that can be used as an imported library or as an api rest running the main.py. There is currently an instance of the api running at https://flanaserver.ddns.net/flanaapis.
Home-page: https://github.com/AlberLC/flanaapis
Author: AlberLC
Project-URL: Bug Tracker, https://github.com/AlberLC/flanaapis/issues
Classifier: Programming Language :: Python :: 3.10
Classifier: License :: OSI Approved :: MIT License
Classifier: Operating System :: OS Independent
Requires-Python: >=3.10
License-File: LICENSE
Requires-Dist: aiohttp
Requires-Dist: beautifulsoup4
Requires-Dist: fastapi
Requires-Dist: flanautils
Requires-Dist: playwright
Requires-Dist: pytube
Requires-Dist: requests
Requires-Dist: ujson
Requires-Dist: uvicorn
Requires-Dist: yt-dlp
